gu_rest_api/__init__.py
gu_rest_api/api_client.py
gu_rest_api/configuration.py
gu_rest_api/driver.py
gu_rest_api/none.py
gu_rest_api/rest.py
gu_rest_api/api/__init__.py
gu_rest_api/api/peer_api.py
gu_rest_api/api/session_api.py
gu_rest_api/models/__init__.py
gu_rest_api/models/blob_info.py
gu_rest_api/models/build_info.py
gu_rest_api/models/command.py
gu_rest_api/models/config_stash.py
gu_rest_api/models/deployment_info.py
gu_rest_api/models/deployment_spec.py
gu_rest_api/models/deployment_spec_image.py
gu_rest_api/models/deployment_status.py
gu_rest_api/models/docker_create_options.py
gu_rest_api/models/docker_net_def.py
gu_rest_api/models/download_file_command.py
gu_rest_api/models/env_type.py
gu_rest_api/models/exec_command.py
gu_rest_api/models/file_format.py
gu_rest_api/models/hub_info.py
gu_rest_api/models/hub_session.py
gu_rest_api/models/hub_session_command.py
gu_rest_api/models/hub_session_touch_command.py
gu_rest_api/models/peer_details.py
gu_rest_api/models/peer_info.py
gu_rest_api/models/process_collection.py
gu_rest_api/models/process_info.py
gu_rest_api/models/start_command.py
gu_rest_api/models/stop_command.py
gu_rest_api/models/upload_file_command.py
gu_rest_api/models/volume_def.py
gu_rest_api/models/volume_def_bind_rw.py
test/__init__.py
test/test_blob_info.py
test/test_build_info.py
test/test_command.py
test/test_config_stash.py
test/test_deployment_info.py
test/test_deployment_spec.py
test/test_deployment_spec_image.py
test/test_deployment_status.py
test/test_docker_create_options.py
test/test_docker_net_def.py
test/test_download_file_command.py
test/test_env_type.py
test/test_exec_command.py
test/test_file_format.py
test/test_hub_info.py
test/test_hub_session.py
test/test_hub_session_command.py
test/test_hub_session_touch_command.py
test/test_peer_api.py
test/test_peer_details.py
test/test_peer_info.py
test/test_process_collection.py
test/test_process_info.py
test/test_session_api.py
test/test_start_command.py
test/test_stop_command.py
gu_python_client-0.2.1.dist-info/METADATA
gu_python_client-0.2.1.dist-info/WHEEL
gu_python_client-0.2.1.dist-info/top_level.txt
gu_python_client-0.2.1.dist-info/RECORD
